LICENSE.txt
MANIFEST.in
README.md
README.rst
setup.py
vcontext/__init__.py
vcontext/context.py
vcontext/tests.py
vcontext.egg-info/PKG-INFO
vcontext.egg-info/SOURCES.txt
vcontext.egg-info/dependency_links.txt
vcontext.egg-info/pbr.json
vcontext.egg-info/requires.txt
vcontext.egg-info/top_level.txt