Metadata-Version: 1.0
Name: vcontext
Version: 0.22
Summary: Context data structure
Home-page: https://github.com/phonkee/vcontext
Author: Peter Vrba
Author-email: phonkee@phonkee.eu
License: UNKNOWN
Platform: UNKNOWN
